climextremes/__init__.py
climextremes/__init__.py~
climextremes-0.3.1.dist-info/LICENSE.txt
climextremes-0.3.1.dist-info/METADATA
climextremes-0.3.1.dist-info/WHEEL
climextremes-0.3.1.dist-info/top_level.txt
climextremes-0.3.1.dist-info/RECORD
